{
  "siteName": "दैनिक पत्रिका",
  "currentDate": "रविवार, २९ मार्च २०२६",
  "navItems": [
    "मुख्य पृष्ठ",
    "देश",
    "अंतरराष्ट्रीय",
    "व्यापार",
    "विज्ञान",
    "खेल",
    "कला"
  ],
  "breakingTitle": "ताज़ा ख़बरें",
  "latestNewsTitle": "बड़ी ख़बरें",
  "readMoreText": "और पढ़ें",
  "breaking": [
    "सरकार ने अर्थव्यवस्था को गति देने के लिए नई नीतियों की घोषणा की",
    "अंतरिक्ष में भारत की नई छलांग: गगनयान मिशन की तैयारी पूरी",
    "शेयर बाजार में भारी उछाल, सेंसेक्स ऐतिहासिक स्तर पर पहुंचा",
    "मौसम अपडेट: कुछ राज्यों में भारी बारिश की चेतावनी जारी"
  ],
  "heroArticle": {
    "title": "अंतरिक्ष में भारत की नई छलांग: गगनयान मिशन की तैयारी पूरी",
    "excerpt": "भारतीय अंतरिक्ष अनुसंधान संगठन (ISRO) ने अपने महत्वाकांक्षी मानव अंतरिक्ष उड़ान मिशन गगनयान के लिए कई महत्वपूर्ण परीक्षण सफलतापूर्वक पूरे कर लिए हैं। इस मिशन का उद्देश्य तीन अंतरिक्ष यात्रियों को पृथ्वी की कक्षा में भेजना है। इस ऐतिहासिक कदम से भारत दुनिया के गिने-चुने देशों में शामिल हो जाएगा।",
    "meta": "विज्ञान • २ घंटे पहले"
  },
  "sideArticles": [
    {
      "title": "शेयर बाजार में भारी उछाल, सेंसेक्स ऐतिहासिक स्तर पर",
      "meta": "व्यापार • ४ घंटे पहले",
      "excerpt": "वैश्विक बाजारों से मिले सकारात्मक संकेतों के कारण निवेशकों में उत्साह देखा गया। आईटी और बैंकिंग सेक्टर में हुई भारी लिवाली ने सेंसेक्स को नई ऊंचाइयों पर पहुँचा दिया, जिससे निवेशकों की संपत्ति में जबरदस्त इजाफा हुआ है। बाजार विशेषज्ञों का मानना है कि विदेशी निवेश के निरंतर प्रवाह और मजबूत आर्थिक आंकड़ों की उम्मीद ने इस ऐतिहासिक तेजी को और अधिक मजबूती प्रदान की है।"
    },
    {
      "title": "क्रिकेट: विश्व कप के लिए भारतीय टीम का ऐलान",
      "meta": "खेल • ५ घंटे पहले",
      "excerpt": "चयनकर्ताओं ने युवा और अनुभवी खिलाड़ियों के बीच बेहतरीन संतुलन बनाया है। टीम में शानदार फॉर्म में चल रहे युवाओं को मौका देने के साथ-साथ अनुभवी दिग्गजों पर भी भरोसा जताया गया है, ताकि दबाव की स्थिति में टीम का मनोबल बना रहे। क्रिकेट प्रेमियों और विशेषज्ञों का मानना है कि यह संतुलित संयोजन आगामी विश्व कप में खिताबी जीत के लिए सबसे प्रबल दावेदार साबित हो सकता है।"
    },
    {
      "title": "मौसम अपडेट: कुछ राज्यों में भारी बारिश की चेतावनी जारी",
      "meta": "मौसम • ८ घंटे पहले",
      "excerpt": "किसानों को अपनी फसलें सुरक्षित रखने की सलाह दी गई है। मौसम विभाग ने अगले ४८ घंटों के दौरान उत्तर और मध्य भारत के कई हिस्सों में तेज हवाओं के साथ भारी वर्षा का अनुमान जताया है।"
    },
    {
      "title": "नई शिक्षा नीति के तहत स्कूलों में बड़े बदलाव",
      "meta": "शिक्षा • १० घंटे पहले",
      "excerpt": "व्यावहारिक ज्ञान और कौशल विकास पर अधिक जोर दिया जाएगा। नई नियमावली के अनुसार, छात्रों को रटने के बजाय रचनात्मक सोच और तकनीकी समझ विकसित करने के लिए प्रोत्साहित किया जाएगा।"
    }
  ],
  "opinions": [
    {
      "author": "रविश कुमार",
      "title": "लोकतंत्र में असहमति की जगह",
      "excerpt": "स्वस्थ लोकतंत्र केवल बहुसंख्यकों के शासन तक सीमित नहीं है, बल्कि यह अल्पसंख्यकों की आवाज़ सुनने का भी माध्यम है। जब समाज में असहमति के स्वरों को दबाया जाता है, तो शासन की जवाबदेही खत्म होने लगती है।"
    },
    {
      "author": "सुषमा स्वराज ठाकुर",
      "title": "पर्यावरण रक्षा: समय की मांग",
      "excerpt": "यदि हम आज प्रकृति का संरक्षण नहीं करेंगे, तो आने वाली पीढ़ियां हमें कभी माफ नहीं करेंगी। जलवायु परिवर्तन के बढ़ते खतरे अब केवल चेतावनी नहीं, बल्कि एक कड़वी हकीकत बन चुके हैं जिसका सामना हमें एकजुट होकर करना होगा।"
    }
  ],
  "quotes": [
    {
      "text": "नवीनतम आर्थिक विश्लेषण के अनुसार, २०२५ में वैश्विक विकास दर ३.०% पर स्थिर रहने का अनुमान है, बशर्ते राष्ट्र बढ़ते व्यापारिक तनावों के बीच नीतिगत स्पष्टता और संस्थागत स्वतंत्रता को प्राथमिकता दें।",
      "author": "आईएमएफ (IMF) वर्ल्ड इकोनॉमिक आउटलुक, अक्टूबर 2025"
    }
  ],
  "gridArticles": [
    {
      "category": "राजनीति",
      "title": "आगामी चुनावों के लिए राजनीतिक दलों ने कमर कसी",
      "excerpt": "नेताओं ने देश भर में जनसभाओं और रैलियों का आयोजन तेज कर दिया है। ग्रामीण क्षेत्रों में विशेष ध्यान दिया जा रहा है।"
    },
    {
      "category": "मनोरंजन",
      "title": "नई फिल्म का टीज़र रिलीज़, दर्शकों में भारी उत्साह",
      "excerpt": "हॉलीवुड और बॉलीवुड की फिल्मों को कड़ी टक्कर देने आ रही है यह नई पेशकश। सोशल मीडिया पर ट्रेंड कर रही है।"
    },
    {
      "category": "प्रौद्योगिकी",
      "title": "आर्टिफिशियल इंटेलिजेंस (AI) का भविष्य और चुनौतियाँ",
      "excerpt": "विशेषज्ञों का मानना है कि एआई आने वाले समय में दुनिया को बदल सकता है, लेकिन रोज़गार पर इसका क्या असर होगा?"
    },
    {
      "category": "स्वास्थ्य",
      "title": "नियमित व्यायाम से हृदय रोगों में भारी कमी",
      "excerpt": "एक नए शोध के अनुसार, दिन में सिर्फ ३० मिनट की सैर आपके दिल को सालों तक स्वस्थ रख सकती है।"
    }
  ],
  "footer": {
    "sections": [
      {
        "title": "समाचार",
        "links": [
          "देश",
          "विदेश",
          "राज्य",
          "शहर"
        ]
      },
      {
        "title": "व्यापार",
        "links": [
          "बाजार",
          "कंपनियां",
          "अर्थव्यवस्था",
          "क्रिप्टो"
        ]
      },
      {
        "title": "मनोरंजन",
        "links": [
          "बॉलीवुड",
          "हॉलीवुड",
          "टेलीविज़न",
          "समीक्षाएं"
        ]
      }
    ],
    "copyright": "© २०२६ दैनिक पत्रिका डिजिटल मीडिया. सर्वाधिकार सुरक्षित।"
  }
}